sco_models-0.2.0.dist-info/DESCRIPTION.rst
sco_models-0.2.0.dist-info/METADATA
sco_models-0.2.0.dist-info/RECORD
sco_models-0.2.0.dist-info/WHEEL
sco_models-0.2.0.dist-info/metadata.json
sco_models-0.2.0.dist-info/top_level.txt
scomodels/__init__.py
