Metadata-Version: 2.0
Name: sco-models
Version: 0.2.0
Summary: Repository for registered models in the Standard Cortical Observer
Home-page: https://github.com/heikomuller/sco-models
Author: Heiko Mueller
Author-email: heiko.muller@gmail.com
License: GPLv3
Keywords: neuroscience vision cortex
Platform: UNKNOWN
Requires-Dist: sco-datastore
